[{"_path":"/career/cv","_dir":"career","_draft":false,"_partial":false,"_locale":"","_empty":false,"title":"简历","description":"","_type":"markdown","_id":"content:8.career:cv.md","_source":"content","_file":"8.career/cv.md","_extension":"md"},{"_path":"/career/tax","_dir":"career","_draft":false,"_partial":false,"_locale":"","_empty":false,"title":"年度报税","description":"2.16起预约退税(以下以2022综合所得年度汇算为例)(也可能是补税)","_type":"markdown","_id":"content:8.career:tax.md","_source":"content","_file":"8.career/tax.md","_extension":"md"}]